openmav/__init__.py
openmav/mav.py
openmav/api/__init__.py
openmav/api/measurements.py
openmav/backends/__init__.py
openmav/backends/model_backend.py
openmav/backends/model_backend_transformers.py
openmav/converters/__init__.py
openmav/converters/data_converter.py
openmav/processors/__init__.py
openmav/processors/state_fetcher.py
openmav/processors/state_processor.py
openmav/view/__init__.py
openmav/view/main_loop_manager.py
openmav/view/panels/__init__.py
openmav/view/panels/internal_panels.py
openmav/view/panels/panel_base.py
openmav/view/panels/panel_creator.py
openmav/view/panels/panel_provider.py
openmav-0.0.12.dist-info/licenses/LICENSE
openmav-0.0.12.dist-info/METADATA
openmav-0.0.12.dist-info/WHEEL
openmav-0.0.12.dist-info/entry_points.txt
openmav-0.0.12.dist-info/top_level.txt
openmav-0.0.12.dist-info/RECORD
