Metadata-Version: 2.4
Name: openmav
Version: 0.0.12
Summary: MAV: Model Activity Visualizer
Author-email: attentionmech <attentionmech@gmail.com>
Project-URL: Homepage, https://github.com/attentionmech/mav
Classifier: Programming Language :: Python :: 3
Classifier: License :: OSI Approved :: MIT License
Requires-Python: >=3.6
License-File: LICENSE
Requires-Dist: rich>=10.11.0
Requires-Dist: torch>=1.5.1
Requires-Dist: transformers>=4.18.0
Dynamic: license-file
